<?xml version="1.0" encoding="utf-8" ?><dwsync><file name="icon-amazon.gif" server="ftp.byethost18.com" local="3422975288" remote="318763443790140912" Dst="-1" /><file name="icon-rating.png" server="ftp.byethost18.com" local="3422975293" remote="318763443790140912" Dst="-1" /><file name="icon-paypal.gif" server="ftp.byethost18.com" local="3422975293" remote="318763443790140912" Dst="-1" /><file name="icon-translate.png" server="ftp.byethost18.com" local="3422975298" remote="318763443790140912" Dst="-1" /><file name="marker_bottom.gif" server="ftp.byethost18.com" local="3422975298" remote="318763443790140912" Dst="-1" /><file name="marker_middle.gif" server="ftp.byethost18.com" local="3422975298" remote="318763443790140912" Dst="-1" /><file name="marker_top.gif" server="ftp.byethost18.com" local="3422975304" remote="318763443790140912" Dst="-1" /><file name="menu-bits.gif" server="ftp.byethost18.com" local="3422975304" remote="318763443790140912" Dst="-1" /><file name="nextgen.png" server="ftp.byethost18.com" local="3422975304" remote="318763443790140912" Dst="-1" /><file name="nextgen_16_color.png" server="ftp.byethost18.com" local="3422975308" remote="318763443790140912" Dst="-1" /><file name="nextgen_16_grey.png" server="ftp.byethost18.com" local="3422975308" remote="318763443790140912" Dst="-1" /><file name="nextgen_32_color.png" server="ftp.byethost18.com" local="3422975309" remote="318763443790140912" Dst="-1" /><file name="nextgen_32_grey.png" server="ftp.byethost18.com" local="3422975313" remote="318763443790140912" Dst="-1" /><file name="select.png" server="ftp.byethost18.com" local="3422975313" remote="318763443790140912" Dst="-1" /></dwsync>